{ "height":8,
 "infinite":false,
 "layers":[
        {
         "data":[14, 14, 14, 14, 14, 14, 14, 14, 14, 14, 14, 14, 14, 14, 14, 14, 14, 14, 14, 14, 14, 14, 14, 14, 14, 14, 14, 14, 14, 14, 14, 14, 14, 14, 14, 14, 14, 14, 14, 14, 14, 14, 14, 14, 14, 14, 14, 14, 14, 14, 14, 14, 14, 14, 14, 14, 14, 14, 14, 14, 14, 14, 14, 14],
         "height":8,
         "name":"Piso",
         "opacity":1,
         "type":"tilelayer",
         "visible":true,
         "width":8,
         "x":0,
         "y":0
        }, 
        {
         "data":[1, 2, 2, 2, 2, 2, 2, 3, 4, 0, 0, 0, 0, 0, 0, 6, 4, 0, 0, 21, 21, 21, 21, 6, 4, 0, 0, 0, 0, 0, 0, 6, 4, 0, 0, 0, 0, 0, 0, 6, 4, 0, 0, 0, 0, 0, 0, 6, 4, 0, 0, 0, 0, 0, 0, 6, 7, 8, 8, 8, 8, 8, 8, 9],
         "height":8,
         "name":"Ambiente",
         "opacity":1,
         "type":"tilelayer",
         "visible":true,
         "width":8,
         "x":0,
         "y":0
        }, 
        {
         "data":[0, 0, 0, 0, 0, 0, 0, 0, 0, 0, 0, 0, 0, 0, 0, 0, 0, 0, 0, 0, 0, 0, 0, 0, 0, 0, 0, 0, 0, 0, 0, 0, 0, 0, 0, 0, 0, 0, 0, 0, 0, 0, 0, 0, 0, 0, 0, 0, 0, 0, 0, 0, 0, 0, 0, 0, 0, 0, 18, 19, 20, 18, 0, 0],
         "height":8,
         "name":"Janela",
         "opacity":1,
         "type":"tilelayer",
         "visible":true,
         "width":8,
         "x":0,
         "y":0
        }],
 "nextobjectid":1,
 "orientation":"orthogonal",
 "renderorder":"right-down",
 "tiledversion":"1.1.5",
 "tileheight":32,
 "tilesets":[
        {
            "columns":3,
            "firstgid":1,
            "image":"..\/..\/..\/assets\/parede.png",
            "imageheight":96,
            "imagewidth":96,
            "margin":0,
            "name":"parede",
            "spacing":0,
            "tilecount":9,
            "tileheight":32,
            "tilewidth":32
        }, 
        {
         "columns":4,
         "firstgid":10,
         "image":"..\/..\/..\/assets\/pisos.png",
         "imageheight":64,
         "imagewidth":128,
         "margin":0,
         "name":"pisos",
         "spacing":0,
         "tilecount":8,
         "tileheight":32,
         "tilewidth":32
        }, 
        {
         "columns":1,
         "firstgid":18,
         "image":"..\/..\/..\/assets\/janela.png",
         "imageheight":32,
         "imagewidth":32,
         "margin":0,
         "name":"janela",
         "spacing":0,
         "tilecount":1,
         "tileheight":32,
         "tilewidth":32
        }, 
        {
         "columns":2,
         "firstgid":19,
         "image":"..\/..\/..\/assets\/porta.png",
         "imageheight":32,
         "imagewidth":64,
         "margin":0,
         "name":"porta",
         "spacing":0,
         "tilecount":2,
         "tileheight":32,
         "tilewidth":32
        }, 
        {
         "columns":1,
         "firstgid":21,
         "image":"..\/..\/..\/assets\/balcao.png",
         "imageheight":32,
         "imagewidth":32,
         "margin":0,
         "name":"balcao",
         "spacing":0,
         "tilecount":1,
         "tileheight":32,
         "tilewidth":32
        }],
 "tilewidth":32,
 "type":"map",
 "version":1,
 "width":8
}